concise/__init__.py
concise/callbacks.py
concise/constraints.py
concise/eval_metrics.py
concise/hyopt.py
concise/initializers.py
concise/layers.py
concise/losses.py
concise/metrics.py
concise/optimizers.py
concise/regularizers.py
concise/data/__init__.py
concise/data/attract.py
concise/data/encode.py
concise/data/hocomoco.py
concise/effects/__init__.py
concise/effects/dropout.py
concise/effects/gradient.py
concise/effects/ism.py
concise/effects/snp_effects.py
concise/effects/util.py
concise/legacy/__init__.py
concise/legacy/analyze.py
concise/legacy/args_sampler.py
concise/legacy/concise.py
concise/legacy/get_data.py
concise/legacy/kmer.py
concise/legacy/models.py
concise/preprocessing/__init__.py
concise/preprocessing/motifs.py
concise/preprocessing/sequence.py
concise/preprocessing/splines.py
concise/preprocessing/structure.py
concise/resources/HOCOMOCOv10_pcms_HUMAN_mono.txt
concise/resources/__init__.py
concise/resources/attract_metadata.txt
concise/resources/attract_pwm.txt
concise/resources/encode_motifs.txt.gz
concise/resources/RNAplfold/E_RNAplfold
concise/resources/RNAplfold/H_RNAplfold
concise/resources/RNAplfold/I_RNAplfold
concise/resources/RNAplfold/M_RNAplfold
concise/resources/RNAplfold/__init__.py
concise/utils/__init__.py
concise/utils/fasta.py
concise/utils/helper.py
concise/utils/letters.py
concise/utils/model_data.py
concise/utils/plot.py
concise/utils/position.py
concise/utils/pwm.py
concise/utils/splines.py
concise/utils/tf_helper.py
tests/__init__.py
tests/devel_concise_quasi_X.py
tests/manual_test_plot.py
tests/setup_concise_load_data.py
tests/setup_effect_test_data.py
tests/test_GAMSmooth.py
tests/test_concise_keras.py
tests/test_conv1d.py
tests/test_effects.py
tests/test_eval.py
tests/test_initializers.py
tests/test_layers.py
tests/test_losses.py
tests/test_metrics.py
tests/test_na_y.py
tests/test_visualization.py
tests/data/test_attract.py
tests/data/test_encode.py
tests/data/test_hocomoco.py
tests/hyopt/__init__.py
tests/hyopt/data.py
concise-0.6.9.dist-info/AUTHORS.md
concise-0.6.9.dist-info/LICENSE
concise-0.6.9.dist-info/METADATA
concise-0.6.9.dist-info/WHEEL
concise-0.6.9.dist-info/top_level.txt
concise-0.6.9.dist-info/RECORD
